{"DE": {"spike_5min": {"date": "2026-04-07", "signals": {"ALV.DE:5min": {"symbol": "ALV.DE", "name": "Allianz SE                    v", "price": 372.5, "prev_close": 367.9, "percent_change": 1.25, "currency": "EUR", "volume": 101324, "avg_volume_50": 801431, "day_high": 372.7, "day_low": 368.6, "screener": "momentum_spike", "country": "DE", "direction": "bullish", "spike": {"timeframe": "5min", "candle_time": "10:20", "direction": "bullish", "body_ratio": 2.37, "volume_ratio": 1.8, "close_ratio": 1.0, "candle_open": 371.6, "candle_close": 372.5, "candle_high": 372.5, "candle_low": 371.6}, "timeframe": "5min", "detected_at": "10:40"}}}, "spike_10min": {"date": "2026-04-07", "signals": {}}, "intraday_booster": {"date": "2026-04-07", "orb5": {}, "orb15": {}}}, "PL": {"intraday_booster": {"date": "2026-04-07", "orb5": {"MRC.WA": {"symbol": "MRC.WA", "name": "MERCATOR", "price": 60.9, "prev_close": 54.2, "percent_change": 12.36, "currency": "PLN", "volume": 76981, "avg_volume_50": 25787, "day_high": 61.2, "day_low": 57.2, "screener": "intraday_booster", "country": "PL", "direction": "bullish", "orb_high": 59.4, "orb_low": 57.3, "current_price": 60.9, "open_price": 59.4, "current_volume": 64658, "r_factor": 2.51, "timeframe": "5min", "detected_at": "10:26"}}, "orb15": {"MRC.WA": {"symbol": "MRC.WA", "name": "MERCATOR", "price": 60.9, "prev_close": 54.2, "percent_change": 12.36, "currency": "PLN", "volume": 76981, "avg_volume_50": 25787, "day_high": 61.2, "day_low": 57.2, "screener": "intraday_booster", "country": "PL", "direction": "bullish", "orb_high": 59.4, "orb_low": 57.2, "current_price": 60.9, "open_price": 59.4, "current_volume": 64658, "r_factor": 2.51, "timeframe": "15min", "detected_at": "10:26"}}}, "spike_5min": {"date": "2026-04-07", "signals": {"ENA.WA:5min": {"symbol": "ENA.WA", "name": "ENEA", "price": 25.64, "prev_close": 26.28, "percent_change": -2.44, "currency": "PLN", "volume": 32971, "avg_volume_50": 420348, "day_high": 26.0, "day_low": 25.44, "screener": "momentum_spike", "country": "PL", "direction": "bullish", "spike": {"timeframe": "5min", "candle_time": "09:55", "direction": "bullish", "body_ratio": 2.5, "volume_ratio": 1.7, "close_ratio": 1.0, "candle_open": 25.48, "candle_close": 25.64, "candle_high": 25.64, "candle_low": 25.46}, "timeframe": "5min", "detected_at": "10:15"}, "ALE.WA:5min": {"symbol": "ALE.WA", "name": "ALLEGRO", "price": 27.04, "prev_close": 26.59, "percent_change": 1.69, "currency": "PLN", "volume": 369658, "avg_volume_50": 4670917, "day_high": 27.04, "day_low": 26.29, "screener": "momentum_spike", "country": "PL", "direction": "bullish", "spike": {"timeframe": "5min", "candle_time": "10:20", "direction": "bullish", "body_ratio": 2.08, "volume_ratio": 2.25, "close_ratio": 1.0, "candle_open": 26.91, "candle_close": 27.04, "candle_high": 27.04, "candle_low": 26.91}, "timeframe": "5min", "detected_at": "10:39"}, "ING.WA:5min": {"symbol": "ING.WA", "name": "INGBSK", "price": 421.0, "prev_close": 418.5, "percent_change": 0.6, "currency": "PLN", "volume": 8632, "avg_volume_50": 38276, "day_high": 421.4, "day_low": 414.0, "screener": "momentum_spike", "country": "PL", "direction": "bullish", "spike": {"timeframe": "5min", "candle_time": "10:30", "direction": "bullish", "body_ratio": 3.91, "volume_ratio": 2.97, "close_ratio": 0.82, "candle_open": 419.2, "candle_close": 421.0, "candle_high": 421.4, "candle_low": 419.2}, "timeframe": "5min", "detected_at": "10:50"}, "XTB.WA:5min": {"symbol": "XTB.WA", "name": "XTB", "price": 97.21, "prev_close": 95.7, "percent_change": 1.58, "currency": "PLN", "volume": 105113, "avg_volume_50": 374060, "day_high": 97.21, "day_low": 95.21, "screener": "momentum_spike", "country": "PL", "direction": "bullish", "spike": {"timeframe": "5min", "candle_time": "10:55", "direction": "bullish", "body_ratio": 2.96, "volume_ratio": 2.01, "close_ratio": 1.0, "candle_open": 96.81, "candle_close": 97.21, "candle_high": 97.21, "candle_low": 96.81}, "timeframe": "5min", "detected_at": "10:57"}, "PZU.WA:5min": {"symbol": "PZU.WA", "name": "PZU", "price": 66.2, "prev_close": 65.88, "percent_change": 0.49, "currency": "PLN", "volume": 562402, "avg_volume_50": 2254504, "day_high": 66.2, "day_low": 65.16, "screener": "momentum_spike", "country": "PL", "direction": "bullish", "spike": {"timeframe": "5min", "candle_time": "10:55", "direction": "bullish", "body_ratio": 2.5, "volume_ratio": 2.38, "close_ratio": 1.0, "candle_open": 65.98, "candle_close": 66.2, "candle_high": 66.2, "candle_low": 65.98}, "timeframe": "5min", "detected_at": "11:14"}, "PEO.WA:5min": {"symbol": "PEO.WA", "name": "PEKAO", "price": 231.7, "prev_close": 224.8, "percent_change": 3.07, "currency": "PLN", "volume": 114574, "avg_volume_50": 710805, "day_high": 231.7, "day_low": 224.3, "screener": "momentum_spike", "country": "PL", "direction": "bullish", "spike": {"timeframe": "5min", "candle_time": "10:55", "direction": "bullish", "body_ratio": 3.24, "volume_ratio": 1.54, "close_ratio": 1.0, "candle_open": 230.5, "candle_close": 231.7, "candle_high": 231.7, "candle_low": 230.4}, "timeframe": "5min", "detected_at": "11:14"}, "KRU.WA:5min": {"symbol": "KRU.WA", "name": "KRUK", "price": 467.5, "prev_close": 462.5, "percent_change": 1.08, "currency": "PLN", "volume": 6124, "avg_volume_50": 29462, "day_high": 467.5, "day_low": 462.6, "screener": "momentum_spike", "country": "PL", "direction": "bullish", "spike": {"timeframe": "5min", "candle_time": "10:55", "direction": "bullish", "body_ratio": 2.04, "volume_ratio": 3.58, "close_ratio": 1.0, "candle_open": 466.4, "candle_close": 467.5, "candle_high": 467.5, "candle_low": 466.2}, "timeframe": "5min", "detected_at": "11:14"}}}, "spike_10min": {"date": "2026-04-07", "signals": {"PKO.WA:10min": {"symbol": "PKO.WA", "name": "PKOBP", "price": 92.36, "prev_close": 90.0, "percent_change": 2.62, "currency": "PLN", "volume": 587164, "avg_volume_50": 2843055, "day_high": 92.36, "day_low": 89.38, "screener": "momentum_spike", "country": "PL", "direction": "bullish", "spike": {"timeframe": "10min", "candle_time": "10:55", "direction": "bullish", "body_ratio": 2.46, "volume_ratio": 2.14, "close_ratio": 1.0, "candle_open": 91.78, "candle_close": 92.36, "candle_high": 92.36, "candle_low": 91.7}, "timeframe": "10min", "detected_at": "11:14"}, "PEO.WA:10min": {"symbol": "PEO.WA", "name": "PEKAO", "price": 231.7, "prev_close": 224.8, "percent_change": 3.07, "currency": "PLN", "volume": 114574, "avg_volume_50": 710805, "day_high": 231.7, "day_low": 224.3, "screener": "momentum_spike", "country": "PL", "direction": "bullish", "spike": {"timeframe": "10min", "candle_time": "10:55", "direction": "bullish", "body_ratio": 2.33, "volume_ratio": 2.8, "close_ratio": 1.0, "candle_open": 230.3, "candle_close": 231.7, "candle_high": 231.7, "candle_low": 229.9}, "timeframe": "10min", "detected_at": "11:14"}, "SPL.WA:10min": {"symbol": "SPL.WA", "name": "SANPL", "price": 619.0, "prev_close": 601.0, "percent_change": 3.0, "currency": "PLN", "volume": 21582, "avg_volume_50": 119702, "day_high": 620.0, "day_low": 596.6, "screener": "momentum_spike", "country": "PL", "direction": "bullish", "spike": {"timeframe": "10min", "candle_time": "10:55", "direction": "bullish", "body_ratio": 1.94, "volume_ratio": 1.9, "close_ratio": 0.77, "candle_open": 616.6, "candle_close": 619.0, "candle_high": 620.0, "candle_low": 615.6}, "timeframe": "10min", "detected_at": "11:14"}, "XTB.WA:10min": {"symbol": "XTB.WA", "name": "XTB", "price": 97.21, "prev_close": 95.7, "percent_change": 1.58, "currency": "PLN", "volume": 105113, "avg_volume_50": 374060, "day_high": 97.21, "day_low": 95.21, "screener": "momentum_spike", "country": "PL", "direction": "bullish", "spike": {"timeframe": "10min", "candle_time": "10:55", "direction": "bullish", "body_ratio": 4.23, "volume_ratio": 2.27, "close_ratio": 1.0, "candle_open": 96.63, "candle_close": 97.21, "candle_high": 97.21, "candle_low": 96.6}, "timeframe": "10min", "detected_at": "11:14"}, "MIL.WA:10min": {"symbol": "MIL.WA", "name": "MILLENNIUM", "price": 17.57, "prev_close": 16.85, "percent_change": 4.27, "currency": "PLN", "volume": 176002, "avg_volume_50": 893454, "day_high": 17.57, "day_low": 16.82, "screener": "momentum_spike", "country": "PL", "direction": "bullish", "spike": {"timeframe": "10min", "candle_time": "10:55", "direction": "bullish", "body_ratio": 2.14, "volume_ratio": 2.67, "close_ratio": 1.0, "candle_open": 17.42, "candle_close": 17.57, "candle_high": 17.57, "candle_low": 17.41}, "timeframe": "10min", "detected_at": "11:14"}}}}, "IN": {"spike_5min": {"date": "2026-04-07", "signals": {"TECHM.NS:5min": {"symbol": "TECHM.NS", "name": "TECH MAHINDRA LIMITED", "price": 1469.2, "prev_close": 1449.5, "percent_change": 1.36, "currency": "INR", "volume": 459210, "avg_volume_50": 2289375, "day_high": 1469.5, "day_low": 1431.3, "screener": "momentum_spike", "country": "IN", "direction": "bullish", "spike": {"timeframe": "5min", "candle_time": "10:45", "direction": "bullish", "body_ratio": 2.92, "volume_ratio": 3.83, "close_ratio": 1.0, "candle_open": 1465.7, "candle_close": 1469.2, "candle_high": 1469.2, "candle_low": 1465.0}, "timeframe": "5min", "detected_at": "10:18"}, "BAJFINANCE.NS:5min": {"symbol": "BAJFINANCE.NS", "name": "BAJAJ FINANCE LIMITED", "price": 851.2, "prev_close": 850.85, "percent_change": 0.04, "currency": "INR", "volume": 4225397, "avg_volume_50": 10291560, "day_high": 862.8, "day_low": 844.45, "screener": "momentum_spike", "country": "IN", "direction": "bullish", "spike": {"timeframe": "5min", "candle_time": "11:15", "direction": "bullish", "body_ratio": 3.08, "volume_ratio": 2.69, "close_ratio": 0.88, "candle_open": 846.95, "candle_close": 851.2, "candle_high": 851.85, "candle_low": 846.4}, "timeframe": "5min", "detected_at": "10:49"}, "GRASIM.NS:5min": {"symbol": "GRASIM.NS", "name": "GRASIM INDUSTRIES LTD", "price": 2594.1, "prev_close": 2614.4, "percent_change": -0.78, "currency": "INR", "volume": 89449, "avg_volume_50": 1096565, "day_high": 2613.8, "day_low": 2576.6, "screener": "momentum_spike", "country": "IN", "direction": "bullish", "spike": {"timeframe": "5min", "candle_time": "11:15", "direction": "bullish", "body_ratio": 2.07, "volume_ratio": 1.99, "close_ratio": 0.85, "candle_open": 2585.2, "candle_close": 2594.1, "candle_high": 2595.9, "candle_low": 2584.2}, "timeframe": "5min", "detected_at": "10:49"}, "HINDUNILVR.NS:5min": {"symbol": "HINDUNILVR.NS", "name": "HINDUSTAN UNILEVER LTD.", "price": 2066.3, "prev_close": 2084.8, "percent_change": -0.89, "currency": "INR", "volume": 585228, "avg_volume_50": 1851331, "day_high": 2076.9, "day_low": 2050.8, "screener": "momentum_spike", "country": "IN", "direction": "bullish", "spike": {"timeframe": "5min", "candle_time": "11:55", "direction": "bullish", "body_ratio": 3.84, "volume_ratio": 4.22, "close_ratio": 0.86, "candle_open": 2063.0, "candle_close": 2066.3, "candle_high": 2067.0, "candle_low": 2062.1}, "timeframe": "5min", "detected_at": "11:30"}, "MARUTI.NS:5min": {"symbol": "MARUTI.NS", "name": "MARUTI SUZUKI INDIA LTD.", "price": 12690.0, "prev_close": 12688.0, "percent_change": 0.02, "currency": "INR", "volume": 116737, "avg_volume_50": 541891, "day_high": 12693.0, "day_low": 12496.0, "screener": "momentum_spike", "country": "IN", "direction": "bullish", "spike": {"timeframe": "5min", "candle_time": "11:55", "direction": "bullish", "body_ratio": 3.27, "volume_ratio": 1.59, "close_ratio": 1.0, "candle_open": 12639.0, "candle_close": 12690.0, "candle_high": 12690.0, "candle_low": 12639.0}, "timeframe": "5min", "detected_at": "11:30"}, "ADANIENT.NS:5min": {"symbol": "ADANIENT.NS", "name": "ADANI ENTERPRISES LIMITED", "price": 1879.6, "prev_close": 1902.2, "percent_change": -1.19, "currency": "INR", "volume": 763966, "avg_volume_50": 1912633, "day_high": 1904.6, "day_low": 1865.0, "screener": "momentum_spike", "country": "IN", "direction": "bullish", "spike": {"timeframe": "5min", "candle_time": "11:55", "direction": "bullish", "body_ratio": 2.78, "volume_ratio": 1.73, "close_ratio": 0.76, "candle_open": 1874.9, "candle_close": 1879.6, "candle_high": 1881.1, "candle_low": 1874.9}, "timeframe": "5min", "detected_at": "11:30"}, "DRREDDY.NS:5min": {"symbol": "DRREDDY.NS", "name": "DR. REDDY S LABORATORIES", "price": 1204.2, "prev_close": 1217.8, "percent_change": -1.12, "currency": "INR", "volume": 588982, "avg_volume_50": 1833242, "day_high": 1211.0, "day_low": 1194.2, "screener": "momentum_spike", "country": "IN", "direction": "bullish", "spike": {"timeframe": "5min", "candle_time": "11:55", "direction": "bullish", "body_ratio": 4.67, "volume_ratio": 7.39, "close_ratio": 1.0, "candle_open": 1200.0, "candle_close": 1204.2, "candle_high": 1204.2, "candle_low": 1199.4}, "timeframe": "5min", "detected_at": "11:30"}, "SBIN.NS:5min": {"symbol": "SBIN.NS", "name": "STATE BANK OF INDIA", "price": 1022.15, "prev_close": 1032.75, "percent_change": -1.03, "currency": "INR", "volume": 6262284, "avg_volume_50": 16383171, "day_high": 1025.3, "day_low": 1012.0, "screener": "momentum_spike", "country": "IN", "direction": "bullish", "spike": {"timeframe": "5min", "candle_time": "13:00", "direction": "bullish", "body_ratio": 5.73, "volume_ratio": 5.46, "close_ratio": 0.91, "candle_open": 1019.15, "candle_close": 1022.5, "candle_high": 1022.9, "candle_low": 1018.5}, "timeframe": "5min", "detected_at": "12:35"}, "INDUSINDBK.NS:5min": {"symbol": "INDUSINDBK.NS", "name": "INDUSIND BANK LIMITED", "price": 783.2, "prev_close": 786.2, "percent_change": -0.38, "currency": "INR", "volume": 657306, "avg_volume_50": 4197759, "day_high": 783.55, "day_low": 770.3, "screener": "momentum_spike", "country": "IN", "direction": "bullish", "spike": {"timeframe": "5min", "candle_time": "13:35", "direction": "bullish", "body_ratio": 2.86, "volume_ratio": 6.0, "close_ratio": 0.96, "candle_open": 780.5, "candle_close": 783.2, "candle_high": 783.3, "candle_low": 780.5}, "timeframe": "5min", "detected_at": "13:07"}, "HEROMOTOCO.NS:5min": {"symbol": "HEROMOTOCO.NS", "name": "HERO MOTOCORP LIMITED", "price": 5033.0, "prev_close": 5103.5, "percent_change": -1.38, "currency": "INR", "volume": 298976, "avg_volume_50": 496442, "day_high": 5084.0, "day_low": 4932.0, "screener": "momentum_spike", "country": "IN", "direction": "bullish", "spike": {"timeframe": "5min", "candle_time": "13:40", "direction": "bullish", "body_ratio": 2.11, "volume_ratio": 2.11, "close_ratio": 0.91, "candle_open": 5020.0, "candle_close": 5033.0, "candle_high": 5034.5, "candle_low": 5018.0}, "timeframe": "5min", "detected_at": "13:13"}, "BAJAJ-AUTO.NS:5min": {"symbol": "BAJAJ-AUTO.NS", "name": "BAJAJ AUTO LIMITED", "price": 9055.0, "prev_close": 8942.5, "percent_change": 1.26, "currency": "INR", "volume": 218354, "avg_volume_50": 334217, "day_high": 9055.0, "day_low": 8800.5, "screener": "momentum_spike", "country": "IN", "direction": "bullish", "spike": {"timeframe": "5min", "candle_time": "13:40", "direction": "bullish", "body_ratio": 4.05, "volume_ratio": 1.88, "close_ratio": 1.0, "candle_open": 9020.0, "candle_close": 9055.0, "candle_high": 9055.0, "candle_low": 9015.0}, "timeframe": "5min", "detected_at": "13:13"}, "SBILIFE.NS:5min": {"symbol": "SBILIFE.NS", "name": "SBI LIFE INSURANCE CO LTD", "price": 1837.6, "prev_close": 1836.8, "percent_change": 0.04, "currency": "INR", "volume": 405121, "avg_volume_50": 1088154, "day_high": 1839.6, "day_low": 1805.5, "screener": "momentum_spike", "country": "IN", "direction": "bullish", "spike": {"timeframe": "5min", "candle_time": "13:50", "direction": "bullish", "body_ratio": 2.11, "volume_ratio": 2.26, "close_ratio": 0.92, "candle_open": 1832.7, "candle_close": 1837.6, "candle_high": 1838.3, "candle_low": 1829.4}, "timeframe": "5min", "detected_at": "13:24"}}}, "spike_10min": {"date": "2026-04-07", "signals": {"HDFCBANK.NS:10min": {"symbol": "HDFCBANK.NS", "name": "HDFC BANK LTD", "price": 768.25, "prev_close": 771.0, "percent_change": -0.36, "currency": "INR", "volume": 16011457, "avg_volume_50": 50097494, "day_high": 769.7, "day_low": 761.0, "screener": "momentum_spike", "country": "IN", "direction": "bullish", "spike": {"timeframe": "10min", "candle_time": "11:20", "direction": "bullish", "body_ratio": 3.68, "volume_ratio": 2.24, "close_ratio": 0.96, "candle_open": 762.85, "candle_close": 767.1, "candle_high": 767.3, "candle_low": 761.95}, "timeframe": "10min", "detected_at": "10:53"}, "BAJFINANCE.NS:10min": {"symbol": "BAJFINANCE.NS", "name": "BAJAJ FINANCE LIMITED", "price": 851.8, "prev_close": 850.85, "percent_change": 0.11, "currency": "INR", "volume": 4394815, "avg_volume_50": 10297207, "day_high": 862.8, "day_low": 844.45, "screener": "momentum_spike", "country": "IN", "direction": "bullish", "spike": {"timeframe": "10min", "candle_time": "11:20", "direction": "bullish", "body_ratio": 2.87, "volume_ratio": 1.66, "close_ratio": 0.91, "candle_open": 846.95, "candle_close": 852.15, "candle_high": 852.7, "candle_low": 846.4}, "timeframe": "10min", "detected_at": "10:53"}, "BRITANNIA.NS:10min": {"symbol": "BRITANNIA.NS", "name": "BRITANNIA INDUSTRIES LTD", "price": 5504.0, "prev_close": 5535.0, "percent_change": -0.56, "currency": "INR", "volume": 70218, "avg_volume_50": 345200, "day_high": 5511.5, "day_low": 5384.0, "screener": "momentum_spike", "country": "IN", "direction": "bullish", "spike": {"timeframe": "10min", "candle_time": "11:30", "direction": "bullish", "body_ratio": 2.32, "volume_ratio": 2.27, "close_ratio": 0.86, "candle_open": 5483.5, "candle_close": 5507.5, "candle_high": 5511.5, "candle_low": 5483.5}, "timeframe": "10min", "detected_at": "11:07"}, "BAJAJ-AUTO.NS:10min": {"symbol": "BAJAJ-AUTO.NS", "name": "BAJAJ AUTO LIMITED", "price": 9064.5, "prev_close": 8942.5, "percent_change": 1.36, "currency": "INR", "volume": 253433, "avg_volume_50": 335387, "day_high": 9088.0, "day_low": 8800.5, "screener": "momentum_spike", "country": "IN", "direction": "bullish", "spike": {"timeframe": "10min", "candle_time": "14:30", "direction": "bullish", "body_ratio": 2.19, "volume_ratio": 1.76, "close_ratio": 0.78, "candle_open": 9044.5, "candle_close": 9075.0, "candle_high": 9084.0, "candle_low": 9044.0}, "timeframe": "10min", "detected_at": "11:25"}, "HINDUNILVR.NS:10min": {"symbol": "HINDUNILVR.NS", "name": "HINDUSTAN UNILEVER LTD.", "price": 2075.6, "prev_close": 2084.8, "percent_change": -0.44, "currency": "INR", "volume": 1447713, "avg_volume_50": 1880081, "day_high": 2079.9, "day_low": 2050.8, "screener": "momentum_spike", "country": "IN", "direction": "bullish", "spike": {"timeframe": "10min", "candle_time": "14:00", "direction": "bullish", "body_ratio": 3.12, "volume_ratio": 2.31, "close_ratio": 0.92, "candle_open": 2065.5, "candle_close": 2074.6, "candle_high": 2075.8, "candle_low": 2060.0}, "timeframe": "10min", "detected_at": "11:34"}, "BPCL.NS:10min": {"symbol": "BPCL.NS", "name": "BHARAT PETROLEUM CORP  LT", "price": 274.75, "prev_close": 278.7, "percent_change": -1.42, "currency": "INR", "volume": 9708500, "avg_volume_50": 13606734, "day_high": 276.6, "day_low": 271.0, "screener": "momentum_spike", "country": "IN", "direction": "bullish", "spike": {"timeframe": "10min", "candle_time": "13:30", "direction": "bullish", "body_ratio": 3.78, "volume_ratio": 1.83, "close_ratio": 0.96, "candle_open": 272.8, "candle_close": 274.5, "candle_high": 274.6, "candle_low": 272.3}, "timeframe": "10min", "detected_at": "11:34"}, "ASIANPAINT.NS:10min": {"symbol": "ASIANPAINT.NS", "name": "ASIAN PAINTS LIMITED", "price": 2185.3, "prev_close": 2184.3, "percent_change": 0.05, "currency": "INR", "volume": 722523, "avg_volume_50": 1194756, "day_high": 2189.1, "day_low": 2145.0, "screener": "momentum_spike", "country": "IN", "direction": "bullish", "spike": {"timeframe": "10min", "candle_time": "14:30", "direction": "bullish", "body_ratio": 5.85, "volume_ratio": 2.28, "close_ratio": 0.72, "candle_open": 2178.4, "candle_close": 2186.0, "candle_high": 2189.1, "candle_low": 2178.2}, "timeframe": "10min", "detected_at": "11:39"}, "SBIN.NS:10min": {"symbol": "SBIN.NS", "name": "STATE BANK OF INDIA", "price": 1022.15, "prev_close": 1032.75, "percent_change": -1.03, "currency": "INR", "volume": 6262284, "avg_volume_50": 16383171, "day_high": 1025.3, "day_low": 1012.0, "screener": "momentum_spike", "country": "IN", "direction": "bullish", "spike": {"timeframe": "10min", "candle_time": "13:00", "direction": "bullish", "body_ratio": 2.75, "volume_ratio": 1.76, "close_ratio": 0.91, "candle_open": 1019.5, "candle_close": 1022.5, "candle_high": 1022.9, "candle_low": 1018.5}, "timeframe": "10min", "detected_at": "12:35"}, "AXISBANK.NS:10min": {"symbol": "AXISBANK.NS", "name": "AXIS BANK LIMITED", "price": 1244.2, "prev_close": 1245.3, "percent_change": -0.09, "currency": "INR", "volume": 4534162, "avg_volume_50": 7521247, "day_high": 1244.7, "day_low": 1221.0, "screener": "momentum_spike", "country": "IN", "direction": "bullish", "spike": {"timeframe": "10min", "candle_time": "14:20", "direction": "bullish", "body_ratio": 1.76, "volume_ratio": 2.51, "close_ratio": 0.93, "candle_open": 1240.8, "candle_close": 1244.2, "candle_high": 1244.5, "candle_low": 1240.1}, "timeframe": "10min", "detected_at": "13:07"}, "TITAN.NS:10min": {"symbol": "TITAN.NS", "name": "TITAN COMPANY LIMITED", "price": 4226.7, "prev_close": 4246.1, "percent_change": -0.46, "currency": "INR", "volume": 639238, "avg_volume_50": 896288, "day_high": 4239.0, "day_low": 4168.8, "screener": "momentum_spike", "country": "IN", "direction": "bullish", "spike": {"timeframe": "10min", "candle_time": "13:40", "direction": "bullish", "body_ratio": 1.96, "volume_ratio": 2.3, "close_ratio": 0.92, "candle_open": 4223.0, "candle_close": 4233.0, "candle_high": 4234.0, "candle_low": 4220.9}, "timeframe": "10min", "detected_at": "13:07"}, "WIPRO.NS:10min": {"symbol": "WIPRO.NS", "name": "WIPRO LTD", "price": 204.09, "prev_close": 197.29, "percent_change": 3.45, "currency": "INR", "volume": 16130137, "avg_volume_50": 17605671, "day_high": 204.24, "day_low": 197.01, "screener": "momentum_spike", "country": "IN", "direction": "bullish", "spike": {"timeframe": "10min", "candle_time": "13:30", "direction": "bullish", "body_ratio": 3.14, "volume_ratio": 1.63, "close_ratio": 0.85, "candle_open": 203.72, "candle_close": 204.1, "candle_high": 204.19, "candle_low": 203.59}, "timeframe": "10min", "detected_at": "13:07"}, "HEROMOTOCO.NS:10min": {"symbol": "HEROMOTOCO.NS", "name": "HERO MOTOCORP LIMITED", "price": 5029.0, "prev_close": 5103.5, "percent_change": -1.46, "currency": "INR", "volume": 305665, "avg_volume_50": 496665, "day_high": 5084.0, "day_low": 4932.0, "screener": "momentum_spike", "country": "IN", "direction": "bullish", "spike": {"timeframe": "10min", "candle_time": "13:40", "direction": "bullish", "body_ratio": 3.37, "volume_ratio": 2.59, "close_ratio": 0.82, "candle_open": 5014.5, "candle_close": 5031.0, "candle_high": 5034.5, "candle_low": 5014.5}, "timeframe": "10min", "detected_at": "13:07"}, "JSWSTEEL.NS:10min": {"symbol": "JSWSTEEL.NS", "name": "JSW STEEL LIMITED", "price": 1139.0, "prev_close": 1133.6, "percent_change": 0.48, "currency": "INR", "volume": 2098683, "avg_volume_50": 1842617, "day_high": 1144.2, "day_low": 1122.3, "screener": "momentum_spike", "country": "IN", "direction": "bullish", "spike": {"timeframe": "10min", "candle_time": "13:30", "direction": "bullish", "body_ratio": 2.69, "volume_ratio": 1.63, "close_ratio": 0.72, "candle_open": 1135.0, "candle_close": 1138.5, "candle_high": 1140.6, "candle_low": 1133.0}, "timeframe": "10min", "detected_at": "13:07"}, "SBILIFE.NS:10min": {"symbol": "SBILIFE.NS", "name": "SBI LIFE INSURANCE CO LTD", "price": 1829.8, "prev_close": 1836.8, "percent_change": -0.38, "currency": "INR", "volume": 354358, "avg_volume_50": 1086461, "day_high": 1833.4, "day_low": 1805.5, "screener": "momentum_spike", "country": "IN", "direction": "bullish", "spike": {"timeframe": "10min", "candle_time": "13:30", "direction": "bullish", "body_ratio": 3.67, "volume_ratio": 2.45, "close_ratio": 0.79, "candle_open": 1826.1, "candle_close": 1831.2, "candle_high": 1833.4, "candle_low": 1823.0}, "timeframe": "10min", "detected_at": "13:07"}, "M&M.NS:10min": {"symbol": "M&M.NS", "name": "MAHINDRA & MAHINDRA LTD", "price": 2992.5, "prev_close": 3021.6, "percent_change": -0.96, "currency": "INR", "volume": 1146779, "avg_volume_50": 3476990, "day_high": 3001.6, "day_low": 2949.5, "screener": "momentum_spike", "country": "IN", "direction": "bullish", "spike": {"timeframe": "10min", "candle_time": "13:30", "direction": "bullish", "body_ratio": 4.81, "volume_ratio": 1.75, "close_ratio": 0.84, "candle_open": 2979.0, "candle_close": 2991.9, "candle_high": 2995.0, "candle_low": 2976.2}, "timeframe": "10min", "detected_at": "13:07"}, "INDUSINDBK.NS:10min": {"symbol": "INDUSINDBK.NS", "name": "INDUSIND BANK LIMITED", "price": 785.0, "prev_close": 786.2, "percent_change": -0.15, "currency": "INR", "volume": 707722, "avg_volume_50": 4199440, "day_high": 786.95, "day_low": 770.3, "screener": "momentum_spike", "country": "IN", "direction": "bullish", "spike": {"timeframe": "10min", "candle_time": "13:40", "direction": "bullish", "body_ratio": 4.11, "volume_ratio": 5.8, "close_ratio": 0.72, "candle_open": 780.5, "candle_close": 783.85, "candle_high": 785.15, "candle_low": 780.5}, "timeframe": "10min", "detected_at": "13:13"}, "ULTRACEMCO.NS:10min": {"symbol": "ULTRACEMCO.NS", "name": "ULTRATECH CEMENT LIMITED", "price": 10908.0, "prev_close": 10955.0, "percent_change": -0.43, "currency": "INR", "volume": 105050, "avg_volume_50": 363693, "day_high": 10922.0, "day_low": 10765.0, "screener": "momentum_spike", "country": "IN", "direction": "bullish", "spike": {"timeframe": "10min", "candle_time": "13:40", "direction": "bullish", "body_ratio": 5.27, "volume_ratio": 2.72, "close_ratio": 0.86, "candle_open": 10873.0, "candle_close": 10912.0, "candle_high": 10919.0, "candle_low": 10870.0}, "timeframe": "10min", "detected_at": "13:19"}, "EICHERMOT.NS:10min": {"symbol": "EICHERMOT.NS", "name": "EICHER MOTORS LTD", "price": 6560.5, "prev_close": 6596.0, "percent_change": -0.54, "currency": "INR", "volume": 708124, "avg_volume_50": 612114, "day_high": 6579.0, "day_low": 6442.0, "screener": "momentum_spike", "country": "IN", "direction": "bullish", "spike": {"timeframe": "10min", "candle_time": "13:40", "direction": "bullish", "body_ratio": 3.37, "volume_ratio": 1.57, "close_ratio": 0.78, "candle_open": 6537.5, "candle_close": 6570.0, "candle_high": 6579.0, "candle_low": 6537.5}, "timeframe": "10min", "detected_at": "13:19"}, "ADANIPORTS.NS:10min": {"symbol": "ADANIPORTS.NS", "name": "ADANI PORT & SEZ LTD", "price": 1379.6, "prev_close": 1387.1, "percent_change": -0.54, "currency": "INR", "volume": 948356, "avg_volume_50": 2625711, "day_high": 1390.0, "day_low": 1368.4, "screener": "momentum_spike", "country": "IN", "direction": "bullish", "spike": {"timeframe": "10min", "candle_time": "13:40", "direction": "bullish", "body_ratio": 4.57, "volume_ratio": 1.96, "close_ratio": 0.98, "candle_open": 1377.7, "candle_close": 1382.0, "candle_high": 1382.1, "candle_low": 1377.7}, "timeframe": "10min", "detected_at": "13:19"}, "NESTLEIND.NS:10min": {"symbol": "NESTLEIND.NS", "name": "NESTLE INDIA LIMITED", "price": 1221.8, "prev_close": 1216.0, "percent_change": 0.48, "currency": "INR", "volume": 821648, "avg_volume_50": 1208218, "day_high": 1222.1, "day_low": 1194.2, "screener": "momentum_spike", "country": "IN", "direction": "bullish", "spike": {"timeframe": "10min", "candle_time": "14:30", "direction": "bullish", "body_ratio": 3.47, "volume_ratio": 1.72, "close_ratio": 0.93, "candle_open": 1218.4, "candle_close": 1221.8, "candle_high": 1222.1, "candle_low": 1218.0}, "timeframe": "10min", "detected_at": "14:06"}, "GRASIM.NS:10min": {"symbol": "GRASIM.NS", "name": "GRASIM INDUSTRIES LTD", "price": 2609.9, "prev_close": 2614.4, "percent_change": -0.17, "currency": "INR", "volume": 308535, "avg_volume_50": 1103868, "day_high": 2627.9, "day_low": 2576.6, "screener": "momentum_spike", "country": "IN", "direction": "bullish", "spike": {"timeframe": "10min", "candle_time": "14:30", "direction": "bullish", "body_ratio": 2.07, "volume_ratio": 2.01, "close_ratio": 0.94, "candle_open": 2608.3, "candle_close": 2614.8, "candle_high": 2615.2, "candle_low": 2608.3}, "timeframe": "10min", "detected_at": "14:06"}}}, "intraday_booster": {"date": "2026-04-07", "orb5": {}, "orb15": {}}}}